molz/__init__.py
molz/molz.py
molz-0.1.2.dist-info/LICENSE
molz-0.1.2.dist-info/METADATA
molz-0.1.2.dist-info/WHEEL
molz-0.1.2.dist-info/top_level.txt
molz-0.1.2.dist-info/RECORD
