Metadata-Version: 2.1
Name: molz
Version: 0.1.2
Summary: Molecular analysis tool
Home-page: https://github.com/LiamWilbraham/molz
Author: Liam Wilbraham
Author-email: liam.wilbraham@glasgow.ac.uk
License: MIT
Platform: UNKNOWN
